build/lib/pydoc2md/__init__.py
build/lib/pydoc2md/cli.py
build/lib/pydoc2md/main.py
build/lib/pydoc2md/utils/__init__.py
build/lib/pydoc2md/utils/parse.py
build/lib/pydoc2md/utils/path_utils.py
build/lib/pydoc2md/utils/write.py
pydoc2md/__init__.py
pydoc2md/cli.py
pydoc2md/main.py
pydoc2md/utils/__init__.py
pydoc2md/utils/parse.py
pydoc2md/utils/path_utils.py
pydoc2md/utils/write.py
pydoc2md-0.0.0.2.dist-info/LICENSE
pydoc2md-0.0.0.2.dist-info/METADATA
pydoc2md-0.0.0.2.dist-info/WHEEL
pydoc2md-0.0.0.2.dist-info/entry_points.txt
pydoc2md-0.0.0.2.dist-info/top_level.txt
pydoc2md-0.0.0.2.dist-info/RECORD
