Metadata-Version: 2.1
Name: pydoc2md
Version: 0.0.0.2
Summary: Converts python code to markdown docs
Home-page: https://github.com/FedeClaudi/pydoc2md
Author: Federico Claudi
License: UNKNOWN
Platform: UNKNOWN
Requires-Python: >=3.6,
Requires-Dist: mdutils
Requires-Dist: astunparse
Requires-Dist: treelib
